vimwiki_markdown.py
vimwiki_markdown-0.4.1.dist-info/LICENSE
vimwiki_markdown-0.4.1.dist-info/METADATA
vimwiki_markdown-0.4.1.dist-info/WHEEL
vimwiki_markdown-0.4.1.dist-info/entry_points.txt
vimwiki_markdown-0.4.1.dist-info/top_level.txt
vimwiki_markdown-0.4.1.dist-info/RECORD
