Metadata-Version: 2.1
Name: vimwiki-markdown
Version: 0.4.1
Summary: vimwiki-markdown: vimwiki markdown file to html with syntax highlighting.
Home-page: https://github.com/WnP/vimwiki_markdown/
Author: Steeve Chailloux
Author-email: github.unrented556@passmail.net
License: MIT License
Platform: UNKNOWN
Classifier: Development Status :: 4 - Beta
Classifier: Environment :: Console
Classifier: Intended Audience :: End Users/Desktop
Classifier: License :: OSI Approved :: MIT License
Classifier: Operating System :: OS Independent
Classifier: Programming Language :: Python :: 3
Classifier: Topic :: Text Editors
License-File: LICENSE
Requires-Dist: Pygments
Requires-Dist: markdown
